lazypredict/__init__.py
lazypredict/supervised.py
lazypredict_nightly-0.3.2.dist-info/AUTHORS.md
lazypredict_nightly-0.3.2.dist-info/LICENSE
lazypredict_nightly-0.3.2.dist-info/METADATA
lazypredict_nightly-0.3.2.dist-info/WHEEL
lazypredict_nightly-0.3.2.dist-info/top_level.txt
lazypredict_nightly-0.3.2.dist-info/RECORD
