Metadata-Version: 2.1
Name: lazypredict-nightly
Version: 0.3.2
Summary: [Updated] Lazy Predict help build a lot of basic models without much code and helps understand which models works better without any parameter tuning
Home-page: https://github.com/nityansuman/lazypredict-nightly
Author: Kumar Nityan Suman
Author-email: nityan.suman@gmail.com
License: MIT license
Keywords: lazypredict,lazypredict-nightly
Classifier: Development Status :: 2 - Pre-Alpha
Classifier: Intended Audience :: Developers
Classifier: License :: OSI Approved :: MIT License
Classifier: Natural Language :: English
Classifier: Programming Language :: Python :: 3
Classifier: Programming Language :: Python :: 3.5
Classifier: Programming Language :: Python :: 3.6
Classifier: Programming Language :: Python :: 3.7
Classifier: Programming Language :: Python :: 3.8
Classifier: Programming Language :: Python :: 3.9
Classifier: Programming Language :: Python :: 3.10
Classifier: Programming Language :: Python :: 3.11
Requires-Python: >=3.6
License-File: LICENSE
License-File: AUTHORS.md
Requires-Dist: click
Requires-Dist: scikit-learn
Requires-Dist: pandas
Requires-Dist: tqdm
Requires-Dist: joblib
Requires-Dist: lightgbm
Requires-Dist: xgboost
Requires-Dist: markupsafe <=2.1.4
